archnemesis/AtmCalc_0.py
archnemesis/Atmosphere_0.py
archnemesis/CIA_0.py
archnemesis/Files.py
archnemesis/ForwardModel_0.py
archnemesis/Layer_0.py
archnemesis/LineData_0.py
archnemesis/Measurement_0.py
archnemesis/Multiple_Scattering_Core.py
archnemesis/NestedSampling_0.py
archnemesis/OptimalEstimation_0.py
archnemesis/Path_0.py
archnemesis/Retrievals.py
archnemesis/Scatter_0.py
archnemesis/Spectroscopy_0.py
archnemesis/Stellar_0.py
archnemesis/Surface_0.py
archnemesis/Telluric_0.py
archnemesis/Variables_0.py
archnemesis/__init__.py
archnemesis/enums.py
archnemesis/Data/__init__.py
archnemesis/Data/aerosol_data.py
archnemesis/Data/constants.py
archnemesis/Data/gas_data.py
archnemesis/Data/lineshapes.py
archnemesis/Data/path_data.py
archnemesis/Data/planet_data.py
archnemesis/Models/ModelBase.py
archnemesis/Models/ModelParameter.py
archnemesis/Models/ModelParameterEntry.py
archnemesis/Models/PostRTModels.py
archnemesis/Models/PreRTModels.py
archnemesis/Models/__init__.py
archnemesis/cfg/__init__.py
archnemesis/cfg/logs.py
archnemesis/cfg/py_3_10_compat.py
archnemesis/cfg/py_3_9_compat.py
archnemesis/database/__init__.py
archnemesis/database/protocols.py
archnemesis/database/datatypes/__init__.py
archnemesis/database/datatypes/gas_descriptor.py
archnemesis/database/datatypes/gas_isotopes.py
archnemesis/database/datatypes/gas_mixture.py
archnemesis/database/datatypes/wave_point.py
archnemesis/database/datatypes/wave_range.py
archnemesis/database/filetypes/__init__.py
archnemesis/database/filetypes/lbltable.py
archnemesis/database/line_database/__init__.py
archnemesis/database/line_database/hitran.py
archnemesis/database/mappings/__init__.py
archnemesis/database/mappings/hitran.py
archnemesis/database/partition_function_database/__init__.py
archnemesis/database/partition_function_database/hitran.py
archnemesis/database/wrappers/__init__.py
archnemesis/database/wrappers/hapi.py
archnemesis/database/wrappers/hapi_monkey_patches.py
archnemesis/helpers/__init__.py
archnemesis-1.0.6.dist-info/licenses/LICENSE
archnemesis-1.0.6.dist-info/METADATA
archnemesis-1.0.6.dist-info/WHEEL
archnemesis-1.0.6.dist-info/top_level.txt
archnemesis-1.0.6.dist-info/RECORD
