Metadata-Version: 2.4
Name: archnemesis
Version: 1.0.6
Summary: Python implementation of the NEMESIS radiative transfer and retrieval code
Home-page: https://github.com/juanaldayparejo/archnemesis-dist
Author: Juan Alday
Project-URL: Documentation, https://archnemesis.readthedocs.io
Project-URL: Source, https://github.com/juanaldayparejo/archnemesis-dist
Project-URL: Tracker, https://github.com/juanaldayparejo/archnemesis-dist/issues
Project-URL: DockerHub, https://hub.docker.com/r/juanaldayparejo/archnemesis
Classifier: Programming Language :: Python :: 3
Classifier: License :: OSI Approved :: GNU General Public License v3 (GPLv3)
Classifier: Operating System :: OS Independent
Requires-Python: >=3.8
License-File: LICENSE
Requires-Dist: numpy
Requires-Dist: matplotlib
Requires-Dist: numba>=0.57.0
Requires-Dist: scipy
Requires-Dist: pymultinest
Requires-Dist: cdsapi
Requires-Dist: joblib
Requires-Dist: h5py
Requires-Dist: basemap
Requires-Dist: pytest
Requires-Dist: corner
Requires-Dist: typing_extensions
Provides-Extra: grib
Requires-Dist: pygrib; extra == "grib"
Provides-Extra: docs
Requires-Dist: sphinx; extra == "docs"
Requires-Dist: sphinx_rtd_theme; extra == "docs"
Provides-Extra: spectroscopy
Requires-Dist: hitran-api; extra == "spectroscopy"
Dynamic: author
Dynamic: classifier
Dynamic: description
Dynamic: description-content-type
Dynamic: home-page
Dynamic: license-file
Dynamic: project-url
Dynamic: provides-extra
Dynamic: requires-dist
Dynamic: requires-python
Dynamic: summary
